copypaster-1.0.0.dist-info/DESCRIPTION.rst
copypaster-1.0.0.dist-info/METADATA
copypaster-1.0.0.dist-info/RECORD
copypaster-1.0.0.dist-info/WHEEL
copypaster-1.0.0.dist-info/metadata.json
copypaster-1.0.0.dist-info/top_level.txt
text_detection/__init__.py
text_detection/api.py
text_detection/detector.py
text_detection/detector_test.py
text_detection/runner.py
