Metadata-Version: 2.0
Name: copypaster
Version: 1.0.0
Summary: Copy text from image
Home-page: UNKNOWN
Author: UNKNOWN
Author-email: UNKNOWN
License: UNKNOWN
Platform: UNKNOWN
